SimpleRL/__init__.py
SimpleRL/envs/__init__.py
SimpleRL/envs/base.py
SimpleRL/envs/hospital.py
SimpleRL/envs/laser_tag.py
SimpleRL/envs/race_car.py
SimpleRL/utils/__init__.py
SimpleRL/utils/hospital_utils.py
SimpleRL/utils/laser_tag_utils.py
SimpleRL/utils/race_car_utils.py
SimpleRL/utils/video.py
SimpleRL-0.0.19.dist-info/LICENSE
SimpleRL-0.0.19.dist-info/METADATA
SimpleRL-0.0.19.dist-info/WHEEL
SimpleRL-0.0.19.dist-info/top_level.txt
SimpleRL-0.0.19.dist-info/RECORD
