Metadata-Version: 2.1
Name: SimpleRL
Version: 0.0.19
Summary: SimpleRL
Home-page: UNKNOWN
Author: Harry Emerson
Author-email: emersonharry8@gmail.com
License: UNKNOWN
Keywords: reinforcement learning,environment
Platform: UNKNOWN
Classifier: Development Status :: 3 - Alpha
Classifier: Intended Audience :: Education
Classifier: Programming Language :: Python :: 2
Classifier: Programming Language :: Python :: 3
Classifier: Operating System :: MacOS :: MacOS X
Classifier: Operating System :: Microsoft :: Windows
Requires-Dist: numpy (>=1.21.4)
Requires-Dist: pygame (>=2.1.0)
Requires-Dist: setuptools (>=58.0.4)
Requires-Dist: imageio (>=2.13.3)
Requires-Dist: scipy (>=1.7.3)
